scrapy_exts/__init__.py
scrapy_exts/extensions/__init__.py
scrapy_exts/middlewares/__init__.py
scrapy_exts/middlewares/base_middleware.py
scrapy_exts/middlewares/fake_useragent.py
scrapy_exts/pipelines/__init__.py
scrapy_exts/pipelines/base_pipeline.py
scrapy_exts/pipelines/mongo_pipeline.py
scrapy_exts/pipelines/mysql_pipeline.py
scrapy_exts/spiders/__init__.py
scrapy_exts/utils/__init__.py
scrapy_exts/utils/ua_util.py
scrapy_exts-0.0.1.dist-info/METADATA
scrapy_exts-0.0.1.dist-info/WHEEL
scrapy_exts-0.0.1.dist-info/top_level.txt
scrapy_exts-0.0.1.dist-info/zip-safe
scrapy_exts-0.0.1.dist-info/RECORD
